plaid_bridges/__init__.py
plaid_bridges/_version.py
plaid_bridges/common/__init__.py
plaid_bridges/common/base.py
plaid_bridges/common/homogeneous.py
plaid_bridges/torch/__init__.py
plaid_bridges/torch/grid_fields_and_scalars.py
plaid_bridges/torch/pyg.py
plaid_bridges-0.1.8.dist-info/licenses/LICENSE.txt
plaid_bridges-0.1.8.dist-info/METADATA
plaid_bridges-0.1.8.dist-info/WHEEL
plaid_bridges-0.1.8.dist-info/top_level.txt
plaid_bridges-0.1.8.dist-info/RECORD
